Workbook

Sheet Cover
B2: NEXUS TECHNOLOGY CORPORATION
B4: Integrated 3-Statement Financial Model | FY2022A – FY2027E
B5: Enterprise Software & Cloud Infrastructure | NASDAQ: NXTC
B8: KEY FINANCIAL HIGHLIGHTS
B9: Metric | C9: FY2024A | D9: FY2025E | E9: FY2026E
B10: Revenue ($mm) | C10: ='Income Statement'!E9 -> 312 | D10: ='Income Statement'!F9 -> 377.04 | E10: ='Income Statement'!G9 -> 455.40574
B11: Revenue Growth | C11: ='Income Statement'!E10 -> 0.15512773 | D11: ='Income Statement'!F10 -> 0.20846154 | E11: ='Income Statement'!G10 -> 0.20784462
B12: Gross Margin | C12: ='Income Statement'!E15 -> 0.684 | D12: ='Income Statement'!F15 -> 0.701 | E12: ='Income Statement'!G15 -> 0.718
B13: EBITDA ($mm) | C13: ='Income Statement'!E30 -> 77.376 | D13: ='Income Statement'!F30 -> 107.07936 | E13: ='Income Statement'!G30 -> 146.18524
B14: EBITDA Margin | C14: =C13/C10 -> 0.248 | D14: =D13/D10 -> 0.284 | E14: =E13/E10 -> 0.321
B15: Net Income ($mm) | C15: ='Income Statement'!E35 -> 51.55176 | D15: ='Income Statement'!F35 -> 74.015074 | E15: ='Income Statement'!G35 -> 103.44599
B16: EPS (Diluted) | C16: ='Income Statement'!E41 -> 3.436784 | D16: ='Income Statement'!F41 -> 4.8694127 | E16: ='Income Statement'!G41 -> 6.6739351
B17: Free Cash Flow ($mm) | C17: ='Cash Flow'!E29 -> 69.73576 | D17: ='Cash Flow'!F29 -> 94.203314 | E17: ='Cash Flow'!G29 -> 126.20817
B20: MODEL INFORMATION
B21: Analyst: | C21: Senior Associate, FP&A
B22: Date: | C22: March 2026
B23: Currency: | C23: USD ($mm unless noted)
B24: Fiscal Year End: | C24: December 31
B25: Projection Period: | C25: FY2025E – FY2027E
B26: Color Coding: | C26: Blue = Input | Black = Formula | Green = Cross-sheet link

Sheet Assumptions
B1: NEXUS TECHNOLOGY CORP — KEY OPERATING ASSUMPTIONS
B3: REVENUE ASSUMPTIONS
B4: Assumption | C4: FY2022A | D4: FY2023A | E4: FY2024A | F4: FY2025E | G4: FY2026E | H4: FY2027E
B5: Subscription Revenue ($mm) | C5: 150.2 | D5: 187.4 | E5: 233.8 | F5: =E5*1.24 -> 289.912 | G5: =F5*1.238 -> 358.91106 | H5: =G5*1.235 -> 443.25515
B6: Professional Services ($mm) | C6: 28.4 | D6: 33.1 | E6: 38.6 | F6: =E6*1.18 -> 45.548 | G6: =F6*1.16 -> 52.83568 | H6: =G6*1.14 -> 60.232675
B7: Maintenance & Support ($mm) | C7: 42.1 | D7: 49.6 | E7: 39.6 | F7: =E7*1.05 -> 41.58 | G7: =F7*1.05 -> 43.659 | H7: =G7*1.05 -> 45.84195
B9: GROWTH RATES
B10: Assumption | C10: FY2022A | D10: FY2023A | E10: FY2024A | F10: FY2025E | G10: FY2026E | H10: FY2027E
B11: Subscription Growth YoY | C11: N/A | D11: =(D5-C5)/C5 -> 0.24766977 | E11: =(E5-D5)/D5 -> 0.24759872 | F11: 0.24 | G11: 0.238 | H11: 0.235
B12: Prof. Services Growth YoY | C12: N/A | D12: =(D6-C6)/C6 -> 0.16549296 | E12: =(E6-D6)/D6 -> 0.16616314 | F12: 0.18 | G12: 0.16 | H12: 0.14
B13: Total Revenue Growth YoY | C13: N/A | D13: =(D14-C14)/C14 -> 0.22383326 | E13: =(E14-D14)/D14 -> 0.15512773 | F13: =(F14-E14)/E14 -> 0.20846154 | G13: =(G14-F14)/F14 -> 0.20784462 | H13: =(H14-G14)/G14 -> 0.20624256
C14: =C5+C6+C7 -> 220.7 | D14: =D5+D6+D7 -> 270.1 | E14: =E5+E6+E7 -> 312 | F14: =F5+F6+F7 -> 377.04 | G14: =G5+G6+G7 -> 455.40574 | H14: =H5+H6+H7 -> 549.32978
B15: MARGIN ASSUMPTIONS
B16: Assumption | C16: FY2022A | D16: FY2023A | E16: FY2024A | F16: FY2025E | G16: FY2026E | H16: FY2027E
B17: Gross Margin % | C17: 0.643 | D17: 0.664 | E17: 0.684 | F17: 0.701 | G17: 0.718 | H17: 0.732
B18: R&D % of Revenue | C18: 0.182 | D18: 0.174 | E18: 0.168 | F18: 0.162 | G18: 0.155 | H18: 0.148
B19: S&M % of Revenue | C19: 0.241 | D19: 0.228 | E19: 0.218 | F19: 0.208 | G19: 0.198 | H19: 0.188
B20: G&A % of Revenue | C20: 0.092 | D20: 0.088 | E20: 0.082 | F20: 0.078 | G20: 0.074 | H20: 0.071
B21: D&A % of Revenue | C21: 0.038 | D21: 0.035 | E21: 0.032 | F21: 0.031 | G21: 0.03 | H21: 0.029
B22: Effective Tax Rate | C22: 0.215 | D22: 0.218 | E22: 0.22 | F22: 0.22 | G22: 0.22 | H22: 0.22
B24: BALANCE SHEET & WORKING CAPITAL ASSUMPTIONS
B25: Assumption | C25: FY2022A | D25: FY2023A | E25: FY2024A | F25: FY2025E | G25: FY2026E | H25: FY2027E
B26: DSO (Days Sales Outstanding) | C26: 42 | D26: 41 | E26: 40 | F26: 39 | G26: 38 | H26: 37
B27: DPO (Days Payable Outstanding) | C27: 32 | D27: 33 | E27: 34 | F27: 35 | G27: 36 | H27: 37
B28: Deferred Revenue (% of Rev) | C28: 0.182 | D28: 0.185 | E28: 0.188 | F28: 0.19 | G28: 0.192 | H28: 0.193
B29: Capex (% of Revenue) | C29: 0.045 | D29: 0.042 | E29: 0.038 | F29: 0.036 | G29: 0.034 | H29: 0.032

Sheet Income Statement
B1: NEXUS TECHNOLOGY CORP — INCOME STATEMENT
B2: All figures in USD millions | Fiscal Year ending December 31
B4: REVENUE
B5: Assumption | C5: FY2022A | D5: FY2023A | E5: FY2024A | F5: FY2025E | G5: FY2026E | H5: FY2027E
B6: Subscription Revenue | C6: =Assumptions!C5 -> 150.2 | D6: =Assumptions!D5 -> 187.4 | E6: =Assumptions!E5 -> 233.8 | F6: =Assumptions!F5 -> 289.912 | G6: =Assumptions!G5 -> 358.91106 | H6: =Assumptions!H5 -> 443.25515
B7: Professional Services | C7: =Assumptions!C6 -> 28.4 | D7: =Assumptions!D6 -> 33.1 | E7: =Assumptions!E6 -> 38.6 | F7: =Assumptions!F6 -> 45.548 | G7: =Assumptions!G6 -> 52.83568 | H7: =Assumptions!H6 -> 60.232675
B8: Maintenance & Support | C8: =Assumptions!C7 -> 42.1 | D8: =Assumptions!D7 -> 49.6 | E8: =Assumptions!E7 -> 39.6 | F8: =Assumptions!F7 -> 41.58 | G8: =Assumptions!G7 -> 43.659 | H8: =Assumptions!H7 -> 45.84195
B9: Total Revenue | C9: =SUM(C6:C8) -> 220.7 | D9: =SUM(D6:D8) -> 270.1 | E9: =SUM(E6:E8) -> 312 | F9: =SUM(F6:F8) -> 377.04 | G9: =SUM(G6:G8) -> 455.40574 | H9: =SUM(H6:H8) -> 549.32978
B10: YoY Growth % | C10: N/A | D10: =(D9-C9)/C9 -> 0.22383326 | E10: =(E9-D9)/D9 -> 0.15512773 | F10: =(F9-E9)/E9 -> 0.20846154 | G10: =(G9-F9)/F9 -> 0.20784462 | H10: =(H9-G9)/G9 -> 0.20624256
B12: COST OF REVENUE & GROSS PROFIT
B13: Cost of Revenue | C13: =C9*(1-Assumptions!C17) -> 78.7899 | D13: =D9*(1-Assumptions!D17) -> 90.7536 | E13: =E9*(1-Assumptions!E17) -> 98.592 | F13: =F9*(1-Assumptions!F17) -> 112.73496 | G13: =G9*(1-Assumptions!G17) -> 128.42442 | H13: =H9*(1-Assumptions!H17) -> 147.22038
B14: Gross Profit | C14: =C9-C13 -> 141.9101 | D14: =D9-D13 -> 179.3464 | E14: =E9-E13 -> 213.408 | F14: =F9-F13 -> 264.30504 | G14: =G9-G13 -> 326.98132 | H14: =H9-H13 -> 402.1094
B15: Gross Margin % | C15: =C14/C9 -> 0.643 | D15: =D14/D9 -> 0.664 | E15: =E14/E9 -> 0.684 | F15: =F14/F9 -> 0.701 | G15: =G14/G9 -> 0.718 | H15: =H14/H9 -> 0.732
B17: OPERATING EXPENSES
B18: Research & Development | C18: =C9*Assumptions!C18 -> 40.1674 | D18: =D9*Assumptions!D18 -> 46.9974 | E18: =E9*Assumptions!E18 -> 52.416 | F18: =F9*Assumptions!F18 -> 61.08048 | G18: =G9*Assumptions!G18 -> 70.587889 | H18: =H9*Assumptions!H18 -> 81.300807
B19: Sales & Marketing | C19: =C9*Assumptions!C19 -> 53.1887 | D19: =D9*Assumptions!D19 -> 61.5828 | E19: =E9*Assumptions!E19 -> 68.016 | F19: =F9*Assumptions!F19 -> 78.42432 | G19: =G9*Assumptions!G19 -> 90.170336 | H19: =H9*Assumptions!H19 -> 103.274
B20: General & Administrative | C20: =C9*Assumptions!C20 -> 20.3044 | D20: =D9*Assumptions!D20 -> 23.7688 | E20: =E9*Assumptions!E20 -> 25.584 | F20: =F9*Assumptions!F20 -> 29.40912 | G20: =G9*Assumptions!G20 -> 33.700024 | H20: =H9*Assumptions!H20 -> 39.002414
B21: Total Operating Expenses | C21: =SUM(C18:C20) -> 113.6605 | D21: =SUM(D18:D20) -> 132.349 | E21: =SUM(E18:E20) -> 146.016 | F21: =SUM(F18:F20) -> 168.91392 | G21: =SUM(G18:G20) -> 194.45825 | H21: =SUM(H18:H20) -> 223.57722
B22: EBIT (Operating Income) | C22: =C14-C21 -> 28.2496 | D22: =D14-D21 -> 46.9974 | E22: =E14-E21 -> 67.392 | F22: =F14-F21 -> 95.39112 | G22: =G14-G21 -> 132.52307 | H22: =H14-H21 -> 178.53218
B23: EBIT Margin % | C23: =C22/C9 -> 0.128 | D23: =D22/D9 -> 0.174 | E23: =E22/E9 -> 0.216 | F23: =F22/F9 -> 0.253 | G23: =G22/G9 -> 0.291 | H23: =H22/H9 -> 0.325
B25: BELOW THE LINE
B26: Depreciation & Amortization | C26: =C9*Assumptions!C21 -> 8.3866 | D26: =D9*Assumptions!D21 -> 9.4535 | E26: =E9*Assumptions!E21 -> 9.984 | F26: =F9*Assumptions!F21 -> 11.68824 | G26: =G9*Assumptions!G21 -> 13.662172 | H26: =H9*Assumptions!H21 -> 15.930564
B27: Interest Income / (Expense) | C27: -3.2 | D27: -2.8 | E27: -2.1 | F27: -1.4 | G27: -0.9 | H27: -0.5
B28: Other Income / (Expense) | C28: 0.4 | D28: 0.6 | E28: 0.8 | F28: 0.9 | G28: 1 | H28: 1.1
B30: EBITDA | C30: =C22+C26 -> 36.6362 | D30: =D22+D26 -> 56.4509 | E30: =E22+E26 -> 77.376 | F30: =F22+F26 -> 107.07936 | G30: =G22+G26 -> 146.18524 | H30: =H22+H26 -> 194.46274
B31: EBITDA Margin % | C31: =C30/C9 -> 0.166 | D31: =D30/D9 -> 0.209 | E31: =E30/E9 -> 0.248 | F31: =F30/F9 -> 0.284 | G31: =G30/G9 -> 0.321 | H31: =H30/H9 -> 0.354
B33: Pre-Tax Income (EBT) | C33: =C22+C27+C28 -> 25.4496 | D33: =D22+D27+D28 -> 44.7974 | E33: =E22+E27+E28 -> 66.092 | F33: =F22+F27+F28 -> 94.89112 | G33: =G22+G27+G28 -> 132.62307 | H33: =H22+H27+H28 -> 179.13218
B34: Income Tax Expense | C34: =C33*Assumptions!C22 -> 5.471664 | D34: =D33*Assumptions!D22 -> 9.7658332 | E34: =E33*Assumptions!E22 -> 14.54024 | F34: =F33*Assumptions!F22 -> 20.876046 | G34: =G33*Assumptions!G22 -> 29.177075 | H34: =H33*Assumptions!H22 -> 39.409079
B35: Net Income | C35: =C33-C34 -> 19.977936 | D35: =D33-D34 -> 35.031567 | E35: =E33-E34 -> 51.55176 | F35: =F33-F34 -> 74.015074 | G35: =G33-G34 -> 103.44599 | H35: =H33-H34 -> 139.7231
B36: Net Margin % | C36: =C35/C9 -> 0.090520779 | D36: =D35/D9 -> 0.12969851 | E36: =E35/E9 -> 0.16523 | F36: =F35/F9 -> 0.19630563 | G36: =G35/G9 -> 0.22715128 | H36: =H35/H9 -> 0.25435195
B38: PER SHARE DATA
B39: Assumption | C39: FY2022A | D39: FY2023A | E39: FY2024A | F39: FY2025E | G39: FY2026E | H39: FY2027E
B40: Diluted Shares Outstanding (mm) | C40: 14.8 | D40: 14.9 | E40: 15 | F40: 15.2 | G40: 15.5 | H40: 15.7
B41: Diluted EPS | C41: =C35/C40 -> 1.3498605 | D41: =D35/D40 -> 2.3511119 | E41: =E35/E40 -> 3.436784 | F41: =F35/F40 -> 4.8694127 | G41: =G35/G40 -> 6.6739351 | H41: =H35/H40 -> 8.8995605

Sheet Cash Flow
B1: NEXUS TECHNOLOGY CORP — CASH FLOW STATEMENT
B2: All figures in USD millions | Indirect Method
B4: OPERATING ACTIVITIES
B5: Assumption | C5: FY2022A | D5: FY2023A | E5: FY2024A | F5: FY2025E | G5: FY2026E | H5: FY2027E
B6: Net Income | C6: ='Income Statement'!C35 -> 19.977936 | D6: ='Income Statement'!D35 -> 35.031567 | E6: ='Income Statement'!E35 -> 51.55176 | F6: ='Income Statement'!F35 -> 74.015074 | G6: ='Income Statement'!G35 -> 103.44599 | H6: ='Income Statement'!H35 -> 139.7231
B7: Depreciation & Amortization | C7: ='Income Statement'!C26 -> 8.3866 | D7: ='Income Statement'!D26 -> 9.4535 | E7: ='Income Statement'!E26 -> 9.984 | F7: ='Income Statement'!F26 -> 11.68824 | G7: ='Income Statement'!G26 -> 13.662172 | H7: ='Income Statement'!H26 -> 15.930564
B8: Stock-Based Compensation | C8: 12.4 | D8: 14.2 | E8: 16.8 | F8: 18.9 | G8: 21.4 | H8: 24.2
B9: Changes in Working Capital:
B10: (Increase) / Decrease in AR | C10: -8.2 | D10: -9.4 | E10: -11.3 | F10: -14.8 | G10: -18.2 | H10: -22.6
B11: Increase / (Decrease) in AP | C11: 2.1 | D11: 2.8 | E11: 3.4 | F11: 4.2 | G11: 5.1 | H11: 6.3
B12: Increase / (Decrease) in Deferred Rev | C12: 8.4 | D12: 9.8 | E12: 11.2 | F12: 14.1 | G12: 17.2 | H12: 20.8
B13: Cash from Operating Activities | C13: =SUM(C6:C12) -> 43.064536 | D13: =SUM(D6:D12) -> 61.885067 | E13: =SUM(E6:E12) -> 81.63576 | F13: =SUM(F6:F12) -> 108.10331 | G13: =SUM(G6:G12) -> 142.60817 | H13: =SUM(H6:H12) -> 184.35366
B15: INVESTING ACTIVITIES
B16: Assumption | C16: FY2022A | D16: FY2023A | E16: FY2024A | F16: FY2025E | G16: FY2026E | H16: FY2027E
B17: Capital Expenditures | C17: -9.6 | D17: -10.2 | E17: -11.9 | F17: -13.9 | G17: -16.4 | H17: -18.8
B18: Acquisitions & Investments | C18: 0 | D18: -45 | E18: 0 | F18: 0 | G18: 0 | H18: 0
B19: Cash from Investing Activities | C19: =SUM(C17:C18) -> -9.6 | D19: =SUM(D17:D18) -> -55.2 | E19: =SUM(E17:E18) -> -11.9 | F19: =SUM(F17:F18) -> -13.9 | G19: =SUM(G17:G18) -> -16.4 | H19: =SUM(H17:H18) -> -18.8
B21: FINANCING ACTIVITIES
B22: Assumption | C22: FY2022A | D22: FY2023A | E22: FY2024A | F22: FY2025E | G22: FY2026E | H22: FY2027E
B23: Debt Issuance / (Repayment) | C23: 0 | D23: 45 | E23: -15 | F23: -15 | G23: -15 | H23: 0
B24: Share Repurchases | C24: -8.4 | D24: -12 | E24: -14.2 | F24: -16.8 | G24: -18.4 | H24: -20
B25: Cash from Financing Activities | C25: =SUM(C23:C24) -> -8.4 | D25: =SUM(D23:D24) -> 33 | E25: =SUM(E23:E24) -> -29.2 | F25: =SUM(F23:F24) -> -31.8 | G25: =SUM(G23:G24) -> -33.4 | H25: =SUM(H23:H24) -> -20
B27: FREE CASH FLOW & LIQUIDITY
B28: Assumption | C28: FY2022A | D28: FY2023A | E28: FY2024A | F28: FY2025E | G28: FY2026E | H28: FY2027E
B29: Free Cash Flow (CFO - Capex) | C29: =C13+C17 -> 33.464536 | D29: =D13+D17 -> 51.685067 | E29: =E13+E17 -> 69.73576 | F29: =F13+F17 -> 94.203314 | G29: =G13+G17 -> 126.20817 | H29: =H13+H17 -> 165.55366
B30: FCF Margin % | C30: =C29/'Income Statement'!C9 -> 0.15162907 | D30: =D29/'Income Statement'!D9 -> 0.1913553 | E30: =E29/'Income Statement'!E9 -> 0.22351205 | F30: =F29/'Income Statement'!F9 -> 0.24984965 | G30: =G29/'Income Statement'!G9 -> 0.27713346 | H30: =H29/'Income Statement'!H9 -> 0.30137391
B32: Net Change in Cash | C32: =C13+C19+C25 -> 25.064536 | D32: =D13+D19+D25 -> 39.685067 | E32: =E13+E19+E25 -> 40.53576 | F32: =F13+F19+F25 -> 62.403314 | G32: =G13+G19+G25 -> 92.808166 | H32: =H13+H19+H25 -> 145.55366
B33: Beginning Cash Balance | C33: 62.4 | D33: 65.7 | E33: 54.8 | F33: 68.2 | G33: 82.1 | H33: 96.8
B34: Ending Cash Balance | C34: =C33+C32 -> 87.464536 | D34: =D33+D32 -> 105.38507 | E34: =E33+E32 -> 95.33576 | F34: =F33+F32 -> 130.60331 | G34: =G33+G32 -> 174.90817 | H34: =H33+H32 -> 242.35366

Sheet Balance Sheet
B1: NEXUS TECHNOLOGY CORP — BALANCE SHEET
B2: All figures in USD millions | Fiscal Year ending December 31
B4: ASSETS
B5: Assumption | C5: FY2022A | D5: FY2023A | E5: FY2024A | F5: FY2025E | G5: FY2026E | H5: FY2027E
B6: Cash & Cash Equivalents | C6: ='Cash Flow'!C34 -> 87.464536 | D6: ='Cash Flow'!D34 -> 105.38507 | E6: ='Cash Flow'!E34 -> 95.33576 | F6: ='Cash Flow'!F34 -> 130.60331 | G6: ='Cash Flow'!G34 -> 174.90817 | H6: ='Cash Flow'!H34 -> 242.35366
B7: Accounts Receivable | C7: 34.2 | D7: 42.4 | E7: 52.1 | F7: 64.8 | G7: 80.4 | H7: 99.8
B8: Prepaid Expenses & Other | C8: 8.2 | D8: 9.4 | E8: 11.2 | F8: 13.8 | G8: 17.1 | H8: 21.2
B9: Total Current Assets | C9: =SUM(C6:C8) -> 129.86454 | D9: =SUM(D6:D8) -> 157.18507 | E9: =SUM(E6:E8) -> 158.63576 | F9: =SUM(F6:F8) -> 209.20331 | G9: =SUM(G6:G8) -> 272.40817 | H9: =SUM(H6:H8) -> 363.35366
B11: Property, Plant & Equipment (net) | C11: 28.4 | D11: 32.6 | E11: 36.8 | F11: 42.1 | G11: 48.6 | H11: 55.4
B12: Intangible Assets & Goodwill | C12: 62.4 | D12: 58.1 | E12: 53.8 | F12: 49.5 | G12: 45.2 | H12: 41
B13: Other Long-Term Assets | C13: 12.4 | D13: 14.2 | E13: 16.8 | F13: 18.9 | G13: 21.4 | H13: 24.2
B14: Total Non-Current Assets | C14: =SUM(C11:C13) -> 103.2 | D14: =SUM(D11:D13) -> 104.9 | E14: =SUM(E11:E13) -> 107.4 | F14: =SUM(F11:F13) -> 110.5 | G14: =SUM(G11:G13) -> 115.2 | H14: =SUM(H11:H13) -> 120.6
B15: TOTAL ASSETS | C15: =C9+C14 -> 233.06454 | D15: =D9+D14 -> 262.08507 | E15: =E9+E14 -> 266.03576 | F15: =F9+F14 -> 319.70331 | G15: =G9+G14 -> 387.60817 | H15: =H9+H14 -> 483.95366
B17: LIABILITIES & SHAREHOLDERS' EQUITY
B18: Assumption | C18: FY2022A | D18: FY2023A | E18: FY2024A | F18: FY2025E | G18: FY2026E | H18: FY2027E
B19: Accounts Payable | C19: 10.2 | D19: 11.8 | E19: 13.4 | F19: 16.2 | G19: 19.8 | H19: 24.1
B20: Deferred Revenue (current) | C20: 24.2 | D20: 28.4 | E20: 33.2 | F20: 39.8 | G20: 48.2 | H20: 58.4
B21: Accrued Liabilities | C21: 18.4 | D21: 21.2 | E21: 24.8 | F21: 28.9 | G21: 33.4 | H21: 38.8
B22: Total Current Liabilities | C22: =SUM(C19:C21) -> 52.8 | D22: =SUM(D19:D21) -> 61.4 | E22: =SUM(E19:E21) -> 71.4 | F22: =SUM(F19:F21) -> 84.9 | G22: =SUM(G19:G21) -> 101.4 | H22: =SUM(H19:H21) -> 121.3
B24: Long-Term Debt | C24: 45 | D24: 86.2 | E24: 71.2 | F24: 56.2 | G24: 41.2 | H24: 41.2
B25: Deferred Revenue (non-current) | C25: 8.4 | D25: 9.8 | E25: 11.2 | F25: 13.4 | G25: 16.2 | H25: 19.8
B26: Other Long-Term Liabilities | C26: 6.2 | D26: 7.1 | E26: 8.2 | F26: 9.4 | G26: 10.8 | H26: 12.4
B27: Total Long-Term Liabilities | C27: =SUM(C24:C26) -> 59.6 | D27: =SUM(D24:D26) -> 103.1 | E27: =SUM(E24:E26) -> 90.6 | F27: =SUM(F24:F26) -> 79 | G27: =SUM(G24:G26) -> 68.2 | H27: =SUM(H24:H26) -> 73.4
B28: TOTAL LIABILITIES | C28: =C22+C27 -> 112.4 | D28: =D22+D27 -> 164.5 | E28: =E22+E27 -> 162 | F28: =F22+F27 -> 163.9 | G28: =G22+G27 -> 169.6 | H28: =H22+H27 -> 194.7
B30: Common Stock & APIC | C30: 128.4 | D30: 142.6 | E30: 159.4 | F30: 178.3 | G30: 199.7 | H30: 223.9
B31: Retained Earnings | C31: 24.2 | D31: 36.8 | E31: 56.2 | F31: 98.4 | G31: 158.2 | H31: 236.8
B32: Treasury Stock | C32: -28.4 | D32: -40.4 | E32: -54.6 | F32: -71.4 | G32: -89.8 | H32: -109.8
B33: Total Shareholders' Equity | C33: =SUM(C30:C32) -> 124.2 | D33: =SUM(D30:D32) -> 139 | E33: =SUM(E30:E32) -> 161 | F33: =SUM(F30:F32) -> 205.3 | G33: =SUM(G30:G32) -> 268.1 | H33: =SUM(H30:H32) -> 350.9
B34: TOTAL LIABILITIES & EQUITY | C34: =C28+C33 -> 236.6 | D34: =D28+D33 -> 303.5 | E34: =E28+E33 -> 323 | F34: =F28+F33 -> 369.2 | G34: =G28+G33 -> 437.7 | H34: =H28+H33 -> 545.6
B36: Balance Check (Assets = Liabilities + Equity) | F36: =IF(ABS(H15-H34)<0.1,"BALANCED","CHECK") -> CHECK

Sheet Sensitivity Analysis
B1: SENSITIVITY ANALYSIS — FY2027E SCENARIOS
B2: Two-variable sensitivity: Revenue Growth Rate vs. EBITDA Margin | FY2027E EBITDA ($mm)
B4: EBITDA SENSITIVITY: REVENUE GROWTH vs. EBITDA MARGIN (FY2027E, $mm)
B5: Rev Growth \ EBITDA Margin | C5: 0.22 | D5: 0.24 | E5: 0.26 | F5: 0.28 | G5: 0.3 | H5: 0.32
B6: 0.15 | C6: 121.7 | D6: 132.8 | E6: 143.8 | F6: 154.9 | G6: 165.9 | H6: 177
B7: 0.18 | C7: 124.9 | D7: 136.2 | E7: 147.6 | F7: 158.9 | G7: 170.3 | H7: 181.6
B8: 0.21 | C8: 128 | D8: 139.7 | E8: 151.3 | F8: 163 | G8: 174.6 | H8: 186.2
B9: 0.24 | C9: 131.2 | D9: 143.1 | E9: 155.1 | F9: 167 | G9: 178.9 | H9: 190.9
B10: 0.27 | C10: 134.4 | D10: 146.6 | E10: 158.8 | F10: 171 | G10: 183.3 | H10: 195.5
B11: 0.3 | C11: 137.6 | D11: 150.1 | E11: 162.6 | F11: 175.1 | G11: 187.6 | H11: 200.1
B14: Color Legend: | C14: > $160mm (Bull Case) | D14: $130-160mm (Base+) | E14: $100-130mm (Base) | F14: $80-100mm (Bear+) | G14: < $80mm (Bear)
B16: SCENARIO ANALYSIS — KEY METRICS BRIDGE
B17: Metric | C17: Bear Case | D17: Base Case | E17: Bull Case
B18: Revenue Growth (CAGR) | C18: 0.18 | D18: =Assumptions!H13 -> 0.20624256 | E18: 0.3
B19: Gross Margin | C19: 0.66 | D19: =Assumptions!H17 -> 0.732 | E19: 0.76
B20: EBITDA Margin | C20: 0.2 | D20: ='Income Statement'!H30/'Income Statement'!H9 -> 0.354 | E20: 0.33
B21: FY2027E Revenue ($mm) | C21: =ROUND('Income Statement'!E9*(1+C18)^3,0) -> 513 | D21: ='Income Statement'!H9 -> 549.32978 | E21: =ROUND('Income Statement'!E9*(1+E18)^3,0) -> 685
B22: FY2027E EBITDA ($mm) | C22: =ROUND(C21*C20,0) -> 103 | D22: ='Income Statement'!H30 -> 194.46274 | E22: =ROUND(E21*E20,0) -> 226
B23: EV/EBITDA Multiple | C23: 18 | D23: 24 | E23: 30
B24: Implied Enterprise Value ($mm) | C24: =ROUND(C22*C23,0) -> 1854 | D24: =ROUND(D22*D23,0) -> 4667 | E24: =ROUND(E22*E23,0) -> 6780
B25: Implied Share Price | C25: =ROUND((C24-'Balance Sheet'!H24+'Balance Sheet'!H6)/'Income Statement'!H40,0) -> 131 | D25: =ROUND((D24-'Balance Sheet'!H24+'Balance Sheet'!H6)/'Income Statement'!H40,0) -> 310 | E25: =ROUND((E24-'Balance Sheet'!H24+'Balance Sheet'!H6)/'Income Statement'!H40,0) -> 445
